Metadata-Version: 2.1
Name: odoo-addon-website-rma
Version: 15.0.1.1.1
Summary: Return Merchandise Authorization (RMA)
Home-page: https://github.com/OCA/rma
Author: Tecnativa, Odoo Community Association (OCA)
Author-email: support@odoo-community.org
License: AGPL-3
Platform: UNKNOWN
Classifier: Programming Language :: Python
Classifier: Framework :: Odoo
Classifier: Framework :: Odoo :: 15.0
Classifier: License :: OSI Approved :: GNU Affero General Public License v3
Classifier: Development Status :: 5 - Production/Stable
Requires-Python: >=3.8
Requires-Dist: odoo-addon-rma <15.1dev,>=15.0dev
Requires-Dist: odoo <15.1dev,>=15.0a
